gym_panda/__init__.py
gym_panda/envs/__init__.py
gym_panda/envs/panda_env.py
gym_panda-0.0.6.dist-info/LICENSE
gym_panda-0.0.6.dist-info/METADATA
gym_panda-0.0.6.dist-info/WHEEL
gym_panda-0.0.6.dist-info/top_level.txt
gym_panda-0.0.6.dist-info/RECORD
