Metadata-Version: 2.1
Name: gym-panda
Version: 0.0.6
Summary: An OpenAI Gym Env for Panda
Home-page: https://github.com/mahyaret/gym-panda
Author: Mahyar Abdeetedal
Author-email: mahyar.etedal@icloud.com
License: UNKNOWN
Platform: UNKNOWN
Classifier: Programming Language :: Python :: 3
Classifier: License :: OSI Approved :: MIT License
Classifier: Operating System :: OS Independent
Requires-Python: >=3.6
Requires-Dist: gym
Requires-Dist: pybullet
Requires-Dist: numpy
